{
    "fields": [
        {
            "name": "ID",
            "labels": "I D",
            "html-type": "number",
            "css-class": "",
            "options": {},
            "html-value": null,
            "validation": "",
            "is-on-index": false,
            "is-on-show": false,
            "is-on-form": false,
            "data-type": "int",
            "data-type-params": [],
            "data-value": null,
            "is-index": false,
            "is-unique": false,
            "is-primary": true,
            "comment": null,
            "is-nullable": true,
            "is-header": false,
            "is-unsigned": true,
            "is-auto-increment": true,
            "is-inline-options": false,
            "is-date": false,
            "date-format": "",
            "cast-as": "",
            "placeholder": "Enter i d here...",
            "delimiter": "; ",
            "range": [],
            "foreign-relation": null,
            "foreign-constraint": null,
            "on-store": null,
            "on-update": null
        },
        {
            "name": "CustomerID",
            "labels": "Customer I D",
            "html-type": "text",
            "css-class": "",
            "options": {},
            "html-value": null,
            "validation": "nullable|string|min:0",
            "is-on-index": true,
            "is-on-show": true,
            "is-on-form": true,
            "data-type": "string",
            "data-type-params": [],
            "data-value": null,
            "is-index": false,
            "is-unique": false,
            "is-primary": false,
            "comment": null,
            "is-nullable": true,
            "is-header": false,
            "is-unsigned": false,
            "is-auto-increment": false,
            "is-inline-options": false,
            "is-date": false,
            "date-format": "",
            "cast-as": "",
            "placeholder": "Enter customer i d here...",
            "delimiter": "; ",
            "range": [],
            "foreign-relation": null,
            "foreign-constraint": null,
            "on-store": null,
            "on-update": null
        },
        {
            "name": "ReceivedAt",
            "labels": "Received At",
            "html-type": "text",
            "css-class": "",
            "options": {},
            "html-value": null,
            "validation": "nullable|string|min:0",
            "is-on-index": true,
            "is-on-show": true,
            "is-on-form": true,
            "data-type": "string",
            "data-type-params": [],
            "data-value": null,
            "is-index": false,
            "is-unique": false,
            "is-primary": false,
            "comment": null,
            "is-nullable": true,
            "is-header": false,
            "is-unsigned": false,
            "is-auto-increment": false,
            "is-inline-options": false,
            "is-date": false,
            "date-format": "",
            "cast-as": "",
            "placeholder": "Enter received at here...",
            "delimiter": "; ",
            "range": [],
            "foreign-relation": null,
            "foreign-constraint": null,
            "on-store": null,
            "on-update": null
        },
        {
            "name": "DeviceReportedTime",
            "labels": "Device Reported Time",
            "html-type": "text",
            "css-class": "",
            "options": {},
            "html-value": null,
            "validation": "nullable|string|min:0",
            "is-on-index": true,
            "is-on-show": true,
            "is-on-form": true,
            "data-type": "string",
            "data-type-params": [],
            "data-value": null,
            "is-index": false,
            "is-unique": false,
            "is-primary": false,
            "comment": null,
            "is-nullable": true,
            "is-header": false,
            "is-unsigned": false,
            "is-auto-increment": false,
            "is-inline-options": false,
            "is-date": false,
            "date-format": "",
            "cast-as": "",
            "placeholder": "Enter device reported time here...",
            "delimiter": "; ",
            "range": [],
            "foreign-relation": null,
            "foreign-constraint": null,
            "on-store": null,
            "on-update": null
        },
        {
            "name": "Facility",
            "labels": "Facility",
            "html-type": "text",
            "css-class": "",
            "options": {},
            "html-value": null,
            "validation": "nullable",
            "is-on-index": true,
            "is-on-show": true,
            "is-on-form": true,
            "data-type": "smallInteger",
            "data-type-params": [],
            "data-value": null,
            "is-index": false,
            "is-unique": false,
            "is-primary": false,
            "comment": null,
            "is-nullable": true,
            "is-header": false,
            "is-unsigned": false,
            "is-auto-increment": false,
            "is-inline-options": false,
            "is-date": false,
            "date-format": "",
            "cast-as": "",
            "placeholder": "Enter facility here...",
            "delimiter": "; ",
            "range": [],
            "foreign-relation": null,
            "foreign-constraint": null,
            "on-store": null,
            "on-update": null
        },
        {
            "name": "Priority",
            "labels": "Priority",
            "html-type": "text",
            "css-class": "",
            "options": {},
            "html-value": null,
            "validation": "nullable",
            "is-on-index": true,
            "is-on-show": true,
            "is-on-form": true,
            "data-type": "smallInteger",
            "data-type-params": [],
            "data-value": null,
            "is-index": false,
            "is-unique": false,
            "is-primary": false,
            "comment": null,
            "is-nullable": true,
            "is-header": false,
            "is-unsigned": false,
            "is-auto-increment": false,
            "is-inline-options": false,
            "is-date": false,
            "date-format": "",
            "cast-as": "",
            "placeholder": "Enter priority here...",
            "delimiter": "; ",
            "range": [],
            "foreign-relation": null,
            "foreign-constraint": null,
            "on-store": null,
            "on-update": null
        },
        {
            "name": "FromHost",
            "labels": "From Host",
            "html-type": "text",
            "css-class": "",
            "options": {},
            "html-value": null,
            "validation": "nullable|string|min:0|max:60",
            "is-on-index": true,
            "is-on-show": true,
            "is-on-form": true,
            "data-type": "string",
            "data-type-params": [
                60
            ],
            "data-value": null,
            "is-index": false,
            "is-unique": false,
            "is-primary": false,
            "comment": null,
            "is-nullable": true,
            "is-header": false,
            "is-unsigned": false,
            "is-auto-increment": false,
            "is-inline-options": false,
            "is-date": false,
            "date-format": "",
            "cast-as": "",
            "placeholder": "Enter from host here...",
            "delimiter": "; ",
            "range": [],
            "foreign-relation": null,
            "foreign-constraint": null,
            "on-store": null,
            "on-update": null
        },
        {
            "name": "Message",
            "labels": "Message",
            "html-type": "textarea",
            "css-class": "",
            "options": {},
            "html-value": null,
            "validation": "nullable|numeric",
            "is-on-index": false,
            "is-on-show": true,
            "is-on-form": true,
            "data-type": "text",
            "data-type-params": [],
            "data-value": null,
            "is-index": false,
            "is-unique": false,
            "is-primary": false,
            "comment": null,
            "is-nullable": true,
            "is-header": false,
            "is-unsigned": false,
            "is-auto-increment": false,
            "is-inline-options": false,
            "is-date": false,
            "date-format": "",
            "cast-as": "",
            "placeholder": "Enter message here...",
            "delimiter": "; ",
            "range": [],
            "foreign-relation": null,
            "foreign-constraint": null,
            "on-store": null,
            "on-update": null
        },
        {
            "name": "NTSeverity",
            "labels": "N T Severity",
            "html-type": "number",
            "css-class": "",
            "options": {},
            "html-value": null,
            "validation": "nullable",
            "is-on-index": false,
            "is-on-show": true,
            "is-on-form": true,
            "data-type": "int",
            "data-type-params": [],
            "data-value": null,
            "is-index": false,
            "is-unique": false,
            "is-primary": false,
            "comment": null,
            "is-nullable": true,
            "is-header": false,
            "is-unsigned": false,
            "is-auto-increment": false,
            "is-inline-options": false,
            "is-date": false,
            "date-format": "",
            "cast-as": "",
            "placeholder": "Enter n t severity here...",
            "delimiter": "; ",
            "range": [],
            "foreign-relation": null,
            "foreign-constraint": null,
            "on-store": null,
            "on-update": null
        },
        {
            "name": "Importance",
            "labels": "Importance",
            "html-type": "number",
            "css-class": "",
            "options": {},
            "html-value": null,
            "validation": "nullable",
            "is-on-index": false,
            "is-on-show": true,
            "is-on-form": true,
            "data-type": "int",
            "data-type-params": [],
            "data-value": null,
            "is-index": false,
            "is-unique": false,
            "is-primary": false,
            "comment": null,
            "is-nullable": true,
            "is-header": false,
            "is-unsigned": false,
            "is-auto-increment": false,
            "is-inline-options": false,
            "is-date": false,
            "date-format": "",
            "cast-as": "",
            "placeholder": "Enter importance here...",
            "delimiter": "; ",
            "range": [],
            "foreign-relation": null,
            "foreign-constraint": null,
            "on-store": null,
            "on-update": null
        },
        {
            "name": "EventSource",
            "labels": "Event Source",
            "html-type": "text",
            "css-class": "",
            "options": {},
            "html-value": null,
            "validation": "nullable|string|min:0|max:60",
            "is-on-index": false,
            "is-on-show": true,
            "is-on-form": true,
            "data-type": "string",
            "data-type-params": [
                60
            ],
            "data-value": null,
            "is-index": false,
            "is-unique": false,
            "is-primary": false,
            "comment": null,
            "is-nullable": true,
            "is-header": false,
            "is-unsigned": false,
            "is-auto-increment": false,
            "is-inline-options": false,
            "is-date": false,
            "date-format": "",
            "cast-as": "",
            "placeholder": "Enter event source here...",
            "delimiter": "; ",
            "range": [],
            "foreign-relation": null,
            "foreign-constraint": null,
            "on-store": null,
            "on-update": null
        },
        {
            "name": "EventUser",
            "labels": "Event User",
            "html-type": "text",
            "css-class": "",
            "options": {},
            "html-value": null,
            "validation": "nullable|string|min:0|max:60",
            "is-on-index": false,
            "is-on-show": true,
            "is-on-form": true,
            "data-type": "string",
            "data-type-params": [
                60
            ],
            "data-value": null,
            "is-index": false,
            "is-unique": false,
            "is-primary": false,
            "comment": null,
            "is-nullable": true,
            "is-header": false,
            "is-unsigned": false,
            "is-auto-increment": false,
            "is-inline-options": false,
            "is-date": false,
            "date-format": "",
            "cast-as": "",
            "placeholder": "Enter event user here...",
            "delimiter": "; ",
            "range": [],
            "foreign-relation": null,
            "foreign-constraint": null,
            "on-store": null,
            "on-update": null
        },
        {
            "name": "EventCategory",
            "labels": "Event Category",
            "html-type": "number",
            "css-class": "",
            "options": {},
            "html-value": null,
            "validation": "nullable",
            "is-on-index": false,
            "is-on-show": true,
            "is-on-form": true,
            "data-type": "int",
            "data-type-params": [],
            "data-value": null,
            "is-index": false,
            "is-unique": false,
            "is-primary": false,
            "comment": null,
            "is-nullable": true,
            "is-header": false,
            "is-unsigned": false,
            "is-auto-increment": false,
            "is-inline-options": false,
            "is-date": false,
            "date-format": "",
            "cast-as": "",
            "placeholder": "Enter event category here...",
            "delimiter": "; ",
            "range": [],
            "foreign-relation": null,
            "foreign-constraint": null,
            "on-store": null,
            "on-update": null
        },
        {
            "name": "EventID",
            "labels": "Event I D",
            "html-type": "number",
            "css-class": "",
            "options": {},
            "html-value": null,
            "validation": "nullable",
            "is-on-index": false,
            "is-on-show": true,
            "is-on-form": true,
            "data-type": "int",
            "data-type-params": [],
            "data-value": null,
            "is-index": false,
            "is-unique": false,
            "is-primary": false,
            "comment": null,
            "is-nullable": true,
            "is-header": false,
            "is-unsigned": false,
            "is-auto-increment": false,
            "is-inline-options": false,
            "is-date": false,
            "date-format": "",
            "cast-as": "",
            "placeholder": "Enter event i d here...",
            "delimiter": "; ",
            "range": [],
            "foreign-relation": null,
            "foreign-constraint": null,
            "on-store": null,
            "on-update": null
        },
        {
            "name": "EventBinaryData",
            "labels": "Event Binary Data",
            "html-type": "textarea",
            "css-class": "",
            "options": {},
            "html-value": null,
            "validation": "nullable",
            "is-on-index": false,
            "is-on-show": true,
            "is-on-form": true,
            "data-type": "text",
            "data-type-params": [],
            "data-value": null,
            "is-index": false,
            "is-unique": false,
            "is-primary": false,
            "comment": null,
            "is-nullable": true,
            "is-header": false,
            "is-unsigned": false,
            "is-auto-increment": false,
            "is-inline-options": false,
            "is-date": false,
            "date-format": "",
            "cast-as": "",
            "placeholder": "Enter event binary data here...",
            "delimiter": "; ",
            "range": [],
            "foreign-relation": null,
            "foreign-constraint": null,
            "on-store": null,
            "on-update": null
        },
        {
            "name": "MaxAvailable",
            "labels": "Max Available",
            "html-type": "number",
            "css-class": "",
            "options": {},
            "html-value": null,
            "validation": "nullable",
            "is-on-index": false,
            "is-on-show": true,
            "is-on-form": true,
            "data-type": "int",
            "data-type-params": [],
            "data-value": null,
            "is-index": false,
            "is-unique": false,
            "is-primary": false,
            "comment": null,
            "is-nullable": true,
            "is-header": false,
            "is-unsigned": false,
            "is-auto-increment": false,
            "is-inline-options": false,
            "is-date": false,
            "date-format": "",
            "cast-as": "",
            "placeholder": "Enter max available here...",
            "delimiter": "; ",
            "range": [],
            "foreign-relation": null,
            "foreign-constraint": null,
            "on-store": null,
            "on-update": null
        },
        {
            "name": "CurrUsage",
            "labels": "Curr Usage",
            "html-type": "number",
            "css-class": "",
            "options": {},
            "html-value": null,
            "validation": "nullable|numeric|min:-2147483648|max:2147483647",
            "is-on-index": false,
            "is-on-show": true,
            "is-on-form": true,
            "data-type": "int",
            "data-type-params": [],
            "data-value": null,
            "is-index": false,
            "is-unique": false,
            "is-primary": false,
            "comment": null,
            "is-nullable": true,
            "is-header": false,
            "is-unsigned": false,
            "is-auto-increment": false,
            "is-inline-options": false,
            "is-date": false,
            "date-format": "",
            "cast-as": "",
            "placeholder": "Enter curr usage here...",
            "delimiter": "; ",
            "range": [],
            "foreign-relation": null,
            "foreign-constraint": null,
            "on-store": null,
            "on-update": null
        },
        {
            "name": "MinUsage",
            "labels": "Min Usage",
            "html-type": "number",
            "css-class": "",
            "options": {},
            "html-value": null,
            "validation": "nullable|numeric|min:-2147483648|max:2147483647",
            "is-on-index": false,
            "is-on-show": true,
            "is-on-form": true,
            "data-type": "int",
            "data-type-params": [],
            "data-value": null,
            "is-index": false,
            "is-unique": false,
            "is-primary": false,
            "comment": null,
            "is-nullable": true,
            "is-header": false,
            "is-unsigned": false,
            "is-auto-increment": false,
            "is-inline-options": false,
            "is-date": false,
            "date-format": "",
            "cast-as": "",
            "placeholder": "Enter min usage here...",
            "delimiter": "; ",
            "range": [],
            "foreign-relation": null,
            "foreign-constraint": null,
            "on-store": null,
            "on-update": null
        },
        {
            "name": "MaxUsage",
            "labels": "Max Usage",
            "html-type": "number",
            "css-class": "",
            "options": {},
            "html-value": null,
            "validation": "nullable|numeric|min:-2147483648|max:2147483647",
            "is-on-index": false,
            "is-on-show": true,
            "is-on-form": true,
            "data-type": "int",
            "data-type-params": [],
            "data-value": null,
            "is-index": false,
            "is-unique": false,
            "is-primary": false,
            "comment": null,
            "is-nullable": true,
            "is-header": false,
            "is-unsigned": false,
            "is-auto-increment": false,
            "is-inline-options": false,
            "is-date": false,
            "date-format": "",
            "cast-as": "",
            "placeholder": "Enter max usage here...",
            "delimiter": "; ",
            "range": [],
            "foreign-relation": null,
            "foreign-constraint": null,
            "on-store": null,
            "on-update": null
        },
        {
            "name": "InfoUnitID",
            "labels": "Info Unit I D",
            "html-type": "number",
            "css-class": "",
            "options": {},
            "html-value": null,
            "validation": "nullable",
            "is-on-index": false,
            "is-on-show": true,
            "is-on-form": true,
            "data-type": "int",
            "data-type-params": [],
            "data-value": null,
            "is-index": false,
            "is-unique": false,
            "is-primary": false,
            "comment": null,
            "is-nullable": true,
            "is-header": false,
            "is-unsigned": false,
            "is-auto-increment": false,
            "is-inline-options": false,
            "is-date": false,
            "date-format": "",
            "cast-as": "",
            "placeholder": "Enter info unit i d here...",
            "delimiter": "; ",
            "range": [],
            "foreign-relation": null,
            "foreign-constraint": null,
            "on-store": null,
            "on-update": null
        },
        {
            "name": "SysLogTag",
            "labels": "Sys Log Tag",
            "html-type": "text",
            "css-class": "",
            "options": {},
            "html-value": null,
            "validation": "nullable|string|min:0|max:60",
            "is-on-index": false,
            "is-on-show": true,
            "is-on-form": true,
            "data-type": "string",
            "data-type-params": [
                60
            ],
            "data-value": null,
            "is-index": false,
            "is-unique": false,
            "is-primary": false,
            "comment": null,
            "is-nullable": true,
            "is-header": false,
            "is-unsigned": false,
            "is-auto-increment": false,
            "is-inline-options": false,
            "is-date": false,
            "date-format": "",
            "cast-as": "",
            "placeholder": "Enter sys log tag here...",
            "delimiter": "; ",
            "range": [],
            "foreign-relation": null,
            "foreign-constraint": null,
            "on-store": null,
            "on-update": null
        },
        {
            "name": "EventLogType",
            "labels": "Event Log Type",
            "html-type": "text",
            "css-class": "",
            "options": {},
            "html-value": null,
            "validation": "nullable|string|min:0|max:60",
            "is-on-index": false,
            "is-on-show": true,
            "is-on-form": true,
            "data-type": "string",
            "data-type-params": [
                60
            ],
            "data-value": null,
            "is-index": false,
            "is-unique": false,
            "is-primary": false,
            "comment": null,
            "is-nullable": true,
            "is-header": false,
            "is-unsigned": false,
            "is-auto-increment": false,
            "is-inline-options": false,
            "is-date": false,
            "date-format": "",
            "cast-as": "",
            "placeholder": "Enter event log type here...",
            "delimiter": "; ",
            "range": [],
            "foreign-relation": null,
            "foreign-constraint": null,
            "on-store": null,
            "on-update": null
        },
        {
            "name": "GenericFileName",
            "labels": "Generic File Name",
            "html-type": "text",
            "css-class": "",
            "options": {},
            "html-value": null,
            "validation": "nullable|string|min:0|max:60",
            "is-on-index": false,
            "is-on-show": true,
            "is-on-form": true,
            "data-type": "string",
            "data-type-params": [
                60
            ],
            "data-value": null,
            "is-index": false,
            "is-unique": false,
            "is-primary": false,
            "comment": null,
            "is-nullable": true,
            "is-header": false,
            "is-unsigned": false,
            "is-auto-increment": false,
            "is-inline-options": false,
            "is-date": false,
            "date-format": "",
            "cast-as": "",
            "placeholder": "Enter generic file name here...",
            "delimiter": "; ",
            "range": [],
            "foreign-relation": null,
            "foreign-constraint": null,
            "on-store": null,
            "on-update": null
        },
        {
            "name": "SystemID",
            "labels": "System I D",
            "html-type": "number",
            "css-class": "",
            "options": {},
            "html-value": null,
            "validation": "nullable",
            "is-on-index": false,
            "is-on-show": true,
            "is-on-form": true,
            "data-type": "int",
            "data-type-params": [],
            "data-value": null,
            "is-index": false,
            "is-unique": false,
            "is-primary": false,
            "comment": null,
            "is-nullable": true,
            "is-header": false,
            "is-unsigned": false,
            "is-auto-increment": false,
            "is-inline-options": false,
            "is-date": false,
            "date-format": "",
            "cast-as": "",
            "placeholder": "Enter system i d here...",
            "delimiter": "; ",
            "range": [],
            "foreign-relation": null,
            "foreign-constraint": null,
            "on-store": null,
            "on-update": null
        }
    ],
    "relations": [],
    "indexes": [],
    "auto-manage-created-and-updated-at": false,
    "table-name": "SystemEvents",
    "protection": {
        "is-model-protected": false,
        "is-controller-protected": false,
        "is-form-request-protected": false,
        "is-languages-protected": false,
        "is-form-view-protected": false,
        "is-index-view-protected": false,
        "is-create-view-protected": false,
        "is-edit-view-protected": false,
        "is-show-view-protected": false
    }
}